nanowire_service_py/__init__.py
nanowire_service_py/logger.py
nanowire_service_py/py.typed
nanowire_service_py/service.py
nanowire_service_py/types.py
nanowire_service_py/utils.py
nanowire_service_py-3.0.2.dist-info/LICENSE
nanowire_service_py-3.0.2.dist-info/WHEEL
nanowire_service_py-3.0.2.dist-info/METADATA
nanowire_service_py-3.0.2.dist-info/RECORD
