Metadata-Version: 2.1
Name: nanowire-service-py
Version: 3.0.2
Summary: Wrapper for interacting with Nanowire platform
Home-page: https://github.com/SpotlightData/nanowire-service-py
License: MIT
Author: SpotlightData
Author-email: info@spotlightdata.co.uk
Classifier: Development Status :: 3 - Alpha
Classifier: Intended Audience :: Developers
Classifier: License :: OSI Approved :: MIT License
Classifier: Operating System :: OS Independent
Classifier: Programming Language :: Python :: 2
Classifier: Programming Language :: Python :: 2.7
Classifier: Programming Language :: Python :: 3
Classifier: Programming Language :: Python :: 3.10
Classifier: Programming Language :: Python :: 3.4
Classifier: Programming Language :: Python :: 3.5
Classifier: Programming Language :: Python :: 3.6
Classifier: Programming Language :: Python :: 3.7
Classifier: Programming Language :: Python :: 3.8
Classifier: Programming Language :: Python :: 3.9
Classifier: Topic :: Software Development :: Libraries :: Python Modules
Requires-Dist: dapr (>=1.2.0,<2.0.0)
Requires-Dist: loguru (>=0.5.3,<0.6.0)
Requires-Dist: pydantic (>=1.8.2,<2.0.0)
Project-URL: Repository, https://github.com/SpotlightData/nanowire-service-py
